gmp/__init__.py
gmp/isprime.py
gmp/lolcat.py
gmp/printing.py
gmp/projecteuler.py
gmp-0.0.16.dist-info/METADATA
gmp-0.0.16.dist-info/WHEEL
gmp-0.0.16.dist-info/top_level.txt
gmp-0.0.16.dist-info/RECORD
