Metadata-Version: 2.1
Name: gmp
Version: 0.0.16
Summary: A little package for GMP
Author: Oz Abramovich
Author-email: oz@abramovich.net
Keywords: python,first package
Classifier: Development Status :: 3 - Alpha
Classifier: Intended Audience :: Education
Classifier: Programming Language :: Python :: 2
Classifier: Programming Language :: Python :: 3
Classifier: Operating System :: MacOS :: MacOS X
Classifier: Operating System :: Microsoft :: Windows
Requires-Dist: string-color
